deeplog/__init__.py
deeplog/__main__.py
deeplog/deeplog.py
deeplog/preprocessor.py
deeplog-0.0.3.dist-info/LICENSE
deeplog-0.0.3.dist-info/METADATA
deeplog-0.0.3.dist-info/WHEEL
deeplog-0.0.3.dist-info/top_level.txt
deeplog-0.0.3.dist-info/RECORD
