Metadata-Version: 2.1
Name: deeplog
Version: 0.0.3
Summary: Pytorch implementation of Deeplog: Anomaly detection and diagnosis from system logs through deep learning
Home-page: https://github.com/Thijsvanede/DeepLog
Author: Thijs van Ede
Author-email: t.s.vanede@utwente.nl
Classifier: Programming Language :: Python :: 3
Classifier: License :: OSI Approved :: MIT License
Classifier: Operating System :: OS Independent
License-File: LICENSE
